haran_utils/__init__.py
haran_utils/main.py
haran_utils/image/__init__.py
haran_utils/image/crop.py
haran_utils/image/filter_imgs.py
haran_utils/image/image.py
haran_utils/image/summarise.py
haran_utils-0.0.4.dist-info/LICENSE
haran_utils-0.0.4.dist-info/METADATA
haran_utils-0.0.4.dist-info/WHEEL
haran_utils-0.0.4.dist-info/entry_points.txt
haran_utils-0.0.4.dist-info/top_level.txt
haran_utils-0.0.4.dist-info/RECORD
