Metadata-Version: 2.1
Name: haran-utils
Version: 0.0.4
Summary: Certain utilities for various tasks
Home-page: https://github.com/haranrk/
Author: Haran Rajkumar
Author-email: haranrajkumar97@gmail.com
License: UNKNOWN
Platform: UNKNOWN
Classifier: Programming Language :: Python :: 3
Classifier: License :: OSI Approved :: MIT License
Classifier: Operating System :: OS Independent
